sqlite_utils_sqlite_vec/__init__.py
sqlite_utils_sqlite_vec-0.1.6.dist-info/METADATA
sqlite_utils_sqlite_vec-0.1.6.dist-info/WHEEL
sqlite_utils_sqlite_vec-0.1.6.dist-info/entry_points.txt
sqlite_utils_sqlite_vec-0.1.6.dist-info/top_level.txt
sqlite_utils_sqlite_vec-0.1.6.dist-info/RECORD
