Metadata-Version: 2.1
Name: sqlite-utils-sqlite-vec
Version: 0.1.6
Home-page: https://TODO.com
Author: TODO
License: MIT License, Apache License, Version 2.0
Requires-Dist: sqlite-utils
Requires-Dist: sqlite-vec (==0.1.6)
